swiss_logger/__init__.py
swiss_logger/log_utils.py
swiss_logger-1.0.3.0.dist-info/LICENSE.txt
swiss_logger-1.0.3.0.dist-info/METADATA
swiss_logger-1.0.3.0.dist-info/WHEEL
swiss_logger-1.0.3.0.dist-info/top_level.txt
swiss_logger-1.0.3.0.dist-info/RECORD
