Metadata-Version: 2.1
Name: swiss-logger
Version: 1.0.3.0
Summary: swiss logger
Home-page: UNKNOWN
Author: lior.yehonatan
Author-email: lior.yehonatan@inel.com
License: UNKNOWN
Platform: UNKNOWN
Requires-Python: >=3.6
Requires-Dist: coloredlogs (==10.0)
Requires-Dist: pyfiglet (==0.8.post1)
